setup.cfg
setup.py
cinvest/__init__.py
cinvest/cinvest.py
cinvest.egg-info/PKG-INFO
cinvest.egg-info/SOURCES.txt
cinvest.egg-info/dependency_links.txt
cinvest.egg-info/not-zip-safe
cinvest.egg-info/top_level.txt