Metadata-Version: 2.1
Name: cinvest
Version: 0.0
Summary: Ticker analysis
Author-email: v.myshlennik@mail.ru
